{
    "version": 1,
    "default_attributes": {
        "font_color": {
            "r": 239,
            "g": 237,
            "b": 235,
            "a": 255
        },
        "font_outline_color": {
            "r": 50,
            "g": 29,
            "b": 25,
            "a": 255
        },
        "font_highlight_color": {
            "r": 18,
            "g": 196,
            "b": 131,
            "a": 255
        },
        "font_highlight2_color": {
            "r": 64,
            "g": 192,
            "b": 255,
            "a": 255
        }
    },
    "script_entries": {
        "tutorial1z": {
            "sign": [
                "Используйте клавиши$$$$",
                "чтобы ходить.",
                "",
                "Двигайте$, чтобы смотреть и поворачиваться.",
                "",
                "Нажмите$, чтобы взаимодействовать",
                "с объектами в мире."
            ],
            "attributes": {
                "font": "fonts/pixelmix.ttf#16#2",
                "horizontal_justify": "center",
                "vertical_justify": "center",
                "line_padding": 0,
                "top_padding": 0,
                "inline_img_adjust_x": 0,
                "word_highlights": [
                    [0,1],
                    [1],
                    [],
                    [0,2,4],
                    [],
                    [0, 2]
                ]
            },
            "variables": [
                {
                    "type": "input_glyph",
                    "value": "Move Forward"
                },
                {
                    "type": "input_glyph",
                    "value": "Move Left"
                },
                {
                    "type": "input_glyph",
                    "value": "Move Backward"
                },
                {
                    "type": "input_glyph",
                    "value": "Move Right"
                },
                {
                    "type": "image",
                    "value": "*#images/ui/Glyphs/Mouse/Mouse_Base_00.png",
                    "sizex": 22,
                    "sizey": 40
                },
                {
                    "type": "input_glyph",
                    "value": "Use"
                }
            ]
        },
        "tutorial1z_gamepad": {
            "sign": [
                "Наклоняйте$, чтобы ходить.",
                "",
                "Наклоняйте$, чтобы смотреть и поворачиваться.",
                "",
                "Нажмите$, чтобы взаимодействовать",
                "с объектами в мире."
            ],
            "attributes": {
                "font": "fonts/pixelmix.ttf#16#2",
                "horizontal_justify": "center",
                "vertical_justify": "center",
                "line_padding": 0,
                "top_padding": 0,
                "inline_img_adjust_x": 0,
                "word_highlights": [
                    [0,2],
                    [],
                    [0,2,4],
                    [],
                    [0,2]
                ]
            },
            "variables": [
                {
                    "type": "image",
                    "value": "*#images/ui/Glyphs/Stick_PS_L_00.png",
                    "sizex": 34,
                    "sizey": 34
                },
                {
                    "type": "image",
                    "value": "*#images/ui/Glyphs/Stick_PS_R_00.png",
                    "sizex": 34,
                    "sizey": 34
                },
                {
                    "type": "input_glyph",
                    "value": "Use"
                }
            ]
        },
        "tutorial1a": {
            "sign": [
                "Нажмите$, чтобы открыть",
                "Меню Паузы.",
                "",
                "Чтобы выйти из любого испытания, выберите",
                "",
                "[ Вернуться в Центр Испытаний ]"
            ],
            "attributes": {
                "font": "fonts/pixelmix.ttf#16#2",
                "horizontal_justify": "center",
                "vertical_justify": "center",
                "line_padding": 0,
                "top_padding": 0,
                "inline_img_adjust_x": 0,
                "word_highlights": [
                    [0],
                    [],
                    [],
                    [],
                    [],
                    [1,2,3,4]
                ]
            },
            "variables": [
                {
                    "type": "input_glyph",
                    "value": "Pause Game"
                }
            ]
        },
        "tutorial1b": {
            "sign": [
                "Экипируйте меч, чтобы",
                "увеличить вашу АТАКУ и",
                "убивать врагов быстрее.",
                "",
                "$"
            ],
            "attributes": {
                "font": "fonts/pixelmix.ttf#16#2",
                "font_highlight_color": {
                    "r": 64,
                    "g": 192,
                    "b": 255,
                    "a": 255
                },
                "horizontal_justify": "center",
                "vertical_justify": "center",
                "line_padding": 0,
                "top_padding": 0,
                "inline_img_adjust_x": 0,
                "word_highlights": [
                    [0],
                    [2]
                ]
            },
            "variables": [
                {
                    "type": "image",
                    "value": "*#data/scripts/tutorial1/sign_sword.png",
                    "sizex": 74,
                    "sizey": 74
                }
            ]
        },
        "tutorial1c": {
            "sign": [
                "$",
                "Экипируйте щиты, чтобы получить КБ,",
                "уменьшая получаемый урон.",
                "",
                "Удерживайте$, чтобы Блокировать,",
                "еще больше увеличивая КБ."
            ],
            "attributes": {
                "font": "fonts/pixelmix.ttf#16#2",
                "font_highlight2_color": {
                    "r": 64,
                    "g": 192,
                    "b": 255,
                    "a": 255
                },
                "horizontal_justify": "center",
                "vertical_justify": "center",
                "line_padding": 0,
                "top_padding": 0,
                "inline_img_adjust_x": 0,
                "word_highlights": [
                    [],
                    [],
                    [],
                    [],
                    [0,2]
                ],
                "word_highlights2": [
                    [],
                    [1,4],
                    [0,1]
                ],
                "video": {
                    "background_img": "data/scripts/video_frame_noalpha.png",
                    "background_border": 8,
                    "path": "data/scripts/tutorial1/shieldequip.ogv",
                    "x": 0,
                    "y": 0,
                    "w": 0,
                    "h": 0
                }
            },
            "variables": [
                {
                    "type": "image",
                    "value": "*#data/scripts/tutorial1/sign_shield.png",
                    "sizex": 0,
                    "sizey": 0
                },
                {
                    "type": "input_glyph",
                    "value": "Defend"
                }
            ]
        },
        "tutorial1d": {
            "sign": [
                "Этот рычаг управляет",
                "воротами возле кровати.",
                "$",
                "Наведите курсор на рычаги и",
                "нажмите$, чтобы переключить."
            ],
            "attributes": {
                "font": "fonts/pixelmix.ttf#16#2",
                "font_highlight2_color": {
                    "r": 64,
                    "g": 192,
                    "b": 255,
                    "a": 255
                },
                "horizontal_justify": "center",
                "vertical_justify": "center",
                "line_padding": 0,
                "top_padding": 0,
                "inline_img_adjust_x": 0,
                "word_highlights": [
                    [],
                    [],
                    [],
                    [0,2],
                    [0,1,2]
                ],
                "word_highlights2": [
                    [1],
                    [0]
                ],
                "video": {
                    "background_img": "data/scripts/video_frame_half_noalpha.png",
                    "background_border": 8,
                    "path": "data/scripts/tutorial1/lever.ogv",
                    "x": 0,
                    "y": 0,
                    "w": 0,
                    "h": 0
                }
            },
            "variables": [
                {
                    "type": "image",
                    "value": "*#data/scripts/tutorial1/sign_levergate.png",
                    "sizex": 189,
                    "sizey": 87
                },
                {
                    "type": "input_glyph",
                    "value": "Use"
                }
            ]
        },
        "tutorial1e": {
            "sign": [
                "Снимайте факелы со",
                "стены с помощью$.",
                "$",
                "Экипированные факелы освещают",
                "путь, но со временем",
                "прогорят."
            ],
            "attributes": {
                "font": "fonts/pixelmix.ttf#16#2",
                "font_highlight2_color": {
                    "r": 64,
                    "g": 192,
                    "b": 255,
                    "a": 255
                },
                "horizontal_justify": "center",
                "vertical_justify": "center",
                "line_padding": 0,
                "top_padding": 0,
                "inline_img_adjust_x": 0,
                "word_highlights": [
                    [0],
                    [2]
                ],
                "word_highlights2": [
                    [],
                    [],
                    [],
                    [],
                    [4,5]
                ],
                "video": {
                    "background_img": "data/scripts/video_frame_half_noalpha.png",
                    "background_border": 8,
                    "path": "data/scripts/tutorial1/torchget.ogv",
                    "x": 0,
                    "y": 0,
                    "w": 0,
                    "h": 0
                }
            },
            "variables": [
                {
                    "type": "input_glyph",
                    "value": "Use"
                },
                {
                    "type": "image",
                    "value": "*#data/scripts/tutorial1/sign_torch.png",
                    "sizex": 74,
                    "sizey": 74
                }
            ]
        },
        "tutorial1e2": {
            "sign": [
                "Откройте лист персонажа,",
                "нажав$.",
                "Нажмите$, чтобы использовать предметы.",
                "Хватайте и перемещайте предметы с помощью$.",
                "Нажмите$ еще раз или$,",
                "чтобы выйти из меню."
            ],
            "attributes": {
                "font": "fonts/pixelmix.ttf#16#2",
                "horizontal_justify": "center",
                "vertical_justify": "center",
                "line_padding": 0,
                "top_padding": 0,
                "inline_img_adjust_x": 0,
                "word_highlights": [
                    [],
                    [1],
                    [0,2,3],
                    [0,2,3,4],
                    [0,2],
                    [1,2,3]
                ],
                "video": {
                    "background_img": "data/scripts/video_frame_noalpha.png",
                    "background_border": 8,
                    "path": "data/scripts/tutorial1/torch_mk.ogv",
                    "x": 0,
                    "y": 0,
                    "w": 0,
                    "h": 0
                }
            },
            "variables": [
                {
                    "type": "input_glyph",
                    "value": "Character Status"
                },
                {
                    "type": "input_glyph",
                    "value": "MenuRightClick"
                },
                {
                    "type": "input_glyph",
                    "value": "MenuLeftClick"
                },
                {
                    "type": "input_glyph",
                    "value": "Character Status"
                },
                {
                    "type": "input_glyph",
                    "value": "MenuCancel"
                }
            ]
        },
        "tutorial1e2_gamepad": {
            "sign": [
                "Откройте лист персонажа,",
                "нажав$.",
                "",
                "Используйте$$$$,",
                "чтобы перемещаться по инвентарю.",
                "",
                "Нажмите$, чтобы использовать предметы.",
                "Используйте$, чтобы хватать и класть.",
                "Нажмите$ или$, чтобы закрыть."
            ],
            "attributes": {
                "font": "fonts/pixelmix.ttf#16#2",
                "horizontal_justify": "center",
                "vertical_justify": "center",
                "line_padding": 0,
                "top_padding": 0,
                "inline_img_adjust_x": 0,
                "word_highlights": [
                    [0],
                    [1],
                    [],
                    [0],
                    [],
                    [],
                    [0,2],
                    [0,2,4],
                    [0,3]
                ],
                "video": {
                    "background_img": "data/scripts/video_frame_noalpha.png",
                    "background_border": 8,
                    "path": "data/scripts/tutorial1/torch_gamepad.ogv",
                    "x": 0,
                    "y": 0,
                    "w": 0,
                    "h": 0
                }
            },
            "variables": [
                {
                    "type": "input_glyph",
                    "value": "Character Status"
                },
                {
                    "type": "input_glyph",
                    "value": "MenuLeft"
                },
                {
                    "type": "input_glyph",
                    "value": "MenuUp"
                },
                {
                    "type": "input_glyph",
                    "value": "MenuDown"
                },
                {
                    "type": "input_glyph",
                    "value": "MenuRight"
                },
                {
                    "type": "input_glyph",
                    "value": "MenuConfirm"
                },
                {
                    "type": "input_glyph",
                    "value": "MenuAlt1"
                },
                {
                    "type": "input_glyph",
                    "value": "Character Status"
                },
                {
                    "type": "input_glyph",
                    "value": "MenuCancel"
                }
            ]
        },
        "tutorial1f": {
            "sign": [
                "Некоторые перчатки могут увеличить",
                "ваш урон без оружия.",
                "",
                "Чтобы использовать атаки без оружия,",
                "снимите ваше оружие."
            ],
            "attributes": {
                "font": "fonts/pixelmix.ttf#16#2",
                "font_highlight2_color": {
                    "r": 64,
                    "g": 192,
                    "b": 255,
                    "a": 255
                },
                "horizontal_justify": "center",
                "vertical_justify": "center",
                "line_padding": 0,
                "top_padding": 0,
                "inline_img_adjust_x": 0,
                "word_highlights": [
                    [],
                    [],
                    [],
                    [],
                    [0,1,2]
                ],
                "word_highlights2": [
                    [1],
                    [1,2]
                ]
            },
            "variables": []
        },
        "tutorial1g": {
            "sign": [
                "Враги атакуют",
                "с постоянной скоростью.",
                "",
                "Блокируйте, пока вас не ударят,",
                "затем быстро атакуйте",
                "и снова блокируйте,",
                "чтобы избежать получения урона."
            ],
            "attributes": {
                "font": "fonts/pixelmix.ttf#16#2",
                "font_highlight2_color": {
                    "r": 64,
                    "g": 192,
                    "b": 255,
                    "a": 255
                },
                "horizontal_justify": "center",
                "vertical_justify": "center",
                "line_padding": 0,
                "top_padding": 0,
                "inline_img_adjust_x": 0,
                "word_highlights": [],
                "word_highlights2": [
                    [1],
                    [3],
                    [],
                    [0],
                    [1,2],
                    [1]
                ],
                "video": {
                    "background_img": "data/scripts/video_frame_half_noalpha.png",
                    "background_border": 8,
                    "path": "data/scripts/tutorial1/block-attack.ogv",
                    "x": 0,
                    "y": 0,
                    "w": 0,
                    "h": 0
                }
            },
            "variables": []
        },
        "tutorial1h": {
            "sign": [
                "Перетаскивайте предметы на панель быстрого доступа",
                "с помощью$, или наведите курсор и",
                "используйте $-$ для назначения.",
                "",
                "Используйте панель быстрого доступа с помощью $-$,",
                "или выделите с помощью $ $ и",
                "затем нажмите$."
            ],
            "attributes": {
                "font": "fonts/pixelmix.ttf#16#2",
                "horizontal_justify": "center",
                "vertical_justify": "center",
                "line_padding": 0,
                "top_padding": 0,
                "inline_img_adjust_x": 0,
                "word_highlights": [
                    [4],
                    [0,3],
                    [3],
                    [],
                    [0,1,2,3],
                    [1,2],
                    [2]
                ],
                "video": {
                    "background_img": "data/scripts/video_frame_noalpha.png",
                    "background_border": 8,
                    "path": "data/scripts/tutorial1/hotbarassign_mk.ogv",
                    "x": 0,
                    "y": 0,
                    "w": 0,
                    "h": 0
                }
            },
            "variables": [
                {
                    "type": "input_glyph",
                    "value": "Attack"
                },
                {
                    "type": "image",
                    "value": "*#images/ui/Glyphs/KeyboardGlyphs/Rendered/Numbers/Unpressed_Text_1_00.png",
                    "sizex": 26,
                    "sizey": 26
                },
                {
                    "type": "image",
                    "value": "*#images/ui/Glyphs/KeyboardGlyphs/Rendered/Numbers/Unpressed_Text_0_00.png",
                    "sizex": 26,
                    "sizey": 26
                },
                {
                    "type": "image",
                    "value": "*#images/ui/Glyphs/KeyboardGlyphs/Rendered/Numbers/Unpressed_Text_1_00.png",
                    "sizex": 26,
                    "sizey": 26
                },
                {
                    "type": "image",
                    "value": "*#images/ui/Glyphs/KeyboardGlyphs/Rendered/Numbers/Unpressed_Text_0_00.png",
                    "sizex": 26,
                    "sizey": 26
                },
                {
                    "type": "input_glyph",
                    "value": "Hotbar Left"
                },
                {
                    "type": "input_glyph",
                    "value": "Hotbar Right"
                },
                {
                    "type": "input_glyph",
                    "value": "Hotbar Up / Select"
                }
            ]
        },
        "tutorial1h_gamepad": {
            "sign": [
                "В инвентаре",
                "хватайте предметы с помощью$ и перемещайте",
                "на панель быстрого доступа с помощью$.",
                "Нажмите$ еще раз,",
                "чтобы поместить предметы в слот.",
                "",
                "Когда инвентарь закрыт,",
                "удерживайте$$ или$, чтобы получить доступ",
                "к слотам$ и$ на панели быстрого доступа."
            ],
            "attributes": {
                "font": "fonts/pixelmix.ttf#16#2",
                "horizontal_justify": "center",
                "vertical_justify": "center",
                "line_padding": 0,
                "top_padding": 0,
                "inline_img_adjust_x": 0,
                "word_highlights": [
                    [],
                    [0,1,2],
                    [],
                    [0],
                    [],
                    [],
                    [],
                    [0,3],
                    [2,3]
                ],
                "video": {
                    "background_img": "data/scripts/video_frame_noalpha.png",
                    "background_border": 8,
                    "path": "data/scripts/tutorial1/hotbarassign_gamepad.ogv",
                    "x": 0,
                    "y": 0,
                    "w": 0,
                    "h": 0
                }
            },
            "variables": [
                {
                    "type": "input_glyph",
                    "value": "MenuAlt1"
                },
                {
                    "type": "input_glyph",
                    "value": "MenuPageRight"
                },
                {
                    "type": "input_glyph",
                    "value": "MenuAlt1"
                },
                {
                    "type": "input_glyph",
                    "value": "Hotbar Left"
                },
                {
                    "type": "input_glyph",
                    "value": "Hotbar Up / Select"
                },
                {
                    "type": "input_glyph",
                    "value": "Hotbar Right"
                },
                {
                    "type": "input_glyph",
                    "value": "HotbarFacebarModifierLeft"
                },
                {
                    "type": "input_glyph",
                    "value": "HotbarFacebarModifierRight"
                }
            ]
        },
        "tutorial1ha": {
            "sign": [
                "Вы не можете одновременно",
                "держать щит и факел!",
                "",
                "Используйте панель быстрого доступа,",
                "чтобы быстро переключаться."
            ],
            "attributes": {
                "font": "fonts/pixelmix.ttf#16#2",
                "horizontal_justify": "center",
                "vertical_justify": "center",
                "line_padding": 0,
                "top_padding": 0,
                "inline_img_adjust_x": 0,
                "word_highlights2": [
                    [],
                    [],
                    [],
                    [],
                    [0,1,2]
                ],
                "video": {
                    "background_img": "data/scripts/video_frame_half_noalpha.png",
                    "background_border": 8,
                    "path": "data/scripts/tutorial1/hotswap_mk.ogv",
                    "x": 0,
                    "y": 0,
                    "w": 0,
                    "h": 0
                }
            },
            "variables": []
        },
        "tutorial1ha_gamepad": {
            "sign": [
                "Вы не можете одновременно",
                "держать щит и факел!",
                "",
                "Используйте панель быстрого доступа,",
                "чтобы быстро переключаться."
            ],
            "attributes": {
                "font": "fonts/pixelmix.ttf#16#2",
                "horizontal_justify": "center",
                "vertical_justify": "center",
                "line_padding": 0,
                "top_padding": 0,
                "inline_img_adjust_x": 0,
                "word_highlights2": [
                    [],
                    [],
                    [],
                    [],
                    [0,1,2]
                ],
                "video": {
                    "background_img": "data/scripts/video_frame_half_noalpha.png",
                    "background_border": 8,
                    "path": "data/scripts/tutorial1/hotswap_gamepad.ogv",
                    "x": 0,
                    "y": 0,
                    "w": 0,
                    "h": 0
                }
            },
            "variables": []
        },
        "tutorial1i": {
            "sign": [
                "Быстро нажимайте$, чтобы Атаковать.",
                "",
                "Удерживайте$, пока ваше",
                "оружие не начнет дрожать для",
                "Критического Удара."
            ],
            "attributes": {
                "font": "fonts/pixelmix.ttf#16#2",
                "horizontal_justify": "center",
                "vertical_justify": "center",
                "line_padding": 0,
                "top_padding": 0,
                "inline_img_adjust_x": 0,
                "word_highlights": [
                    [1,3],
                    [],
                    [0],
                    [1],
                    [1,2]
                ],
                "video": {
                    "background_img": "data/scripts/video_frame_half_noalpha.png",
                    "background_border": 8,
                    "path": "data/scripts/tutorial1/attacks.ogv",
                    "x": 0,
                    "y": 0,
                    "w": 0,
                    "h": 0
                }
            },
            "variables": [
                {
                    "type": "input_glyph",
                    "value": "Attack"
                },
                {
                    "type": "input_glyph",
                    "value": "Attack"
                }
            ]
        },
        "tutorial1i2": {
            "sign": [
                "Посмотрите Лист Персонажа,",
                "нажав$, справа.",
                "",
                "Наведите курсор с помощью$, чтобы узнать",
                "о характеристиках, таких как АТАКА."
            ],
            "attributes": {
                "font": "fonts/pixelmix.ttf#16#2",
                "font_highlight2_color": {
                    "r": 64,
                    "g": 192,
                    "b": 255,
                    "a": 255
                },
                "horizontal_justify": "center",
                "vertical_justify": "center",
                "line_padding": 0,
                "top_padding": 0,
                "inline_img_adjust_x": 0,
                "word_highlights": [
                    [],
                    [0],
                    [],
                    [0,1],
                    []
                ],
                "word_highlights2": [
                    [2,3],
                    [],
                    [],
                    [],
                    [3]
                ],
                "video": {
                    "background_img": "data/scripts/video_frame_noalpha.png",
                    "background_border": 8,
                    "path": "data/scripts/tutorial1/atk_mk.ogv",
                    "x": 0,
                    "y": 0,
                    "w": 0,
                    "h": 0
                }
            },
            "variables": [
                {
                    "type": "input_glyph",
                    "value": "Character Status"
                },
                {
                    "type": "image",
                    "value": "*#images/ui/Glyphs/Mouse/Mouse_Base_00.png",
                    "sizex": 22,
                    "sizey": 40
                }
            ]
        },
        "tutorial1i2_gamepad": {
            "sign": [
                "Посмотрите Лист Персонажа,",
                "нажав$, справа.",
                "",
                "Нажмите$ дважды и узнайте",
                "о характеристиках, таких как АТАКА,",
                "перемещаясь к ним",
                "и удерживая$."
            ],
            "attributes": {
                "font": "fonts/pixelmix.ttf#16#2",
                "font_highlight2_color": {
                    "r": 64,
                    "g": 192,
                    "b": 255,
                    "a": 255
                },
                "horizontal_justify": "center",
                "vertical_justify": "center",
                "line_padding": 0,
                "top_padding": 0,
                "inline_img_adjust_x": 0,
                "word_highlights": [
                    [],
                    [0],
                    [],
                    [0,1],
                    [],
                    [],
                    [1]
                ],
                "word_highlights2": [
                    [2,3],
                    [],
                    [],
                    [],
                    [3],
                    []
                ],
                "video": {
                    "background_img": "data/scripts/video_frame_noalpha.png",
                    "background_border": 8,
                    "path": "data/scripts/tutorial1/atk_gamepad.ogv",
                    "x": 0,
                    "y": 0,
                    "w": 0,
                    "h": 0
                }
            },
            "variables": [
                {
                    "type": "input_glyph",
                    "value": "Character Status"
                },
                {
                    "type": "input_glyph",
                    "value": "MenuPageRight"
                },
                {
                    "type": "input_glyph",
                    "value": "MenuConfirm"
                }
            ]
        },
        "tutorial1j": {
            "sign": [
                "Ваше понимание",
                "атак, блокирования и",
                "типов оружия",
                "будет проверено.",
                "",
                "У каждого испытания есть",
                "финальное испытание."
            ],
            "attributes": {
                "font": "fonts/pixelmix.ttf#16#2",
                "font_highlight2_color": {
                    "r": 64,
                    "g": 192,
                    "b": 255,
                    "a": 255
                },
                "horizontal_justify": "center",
                "vertical_justify": "center",
                "line_padding": 0,
                "top_padding": 0,
                "inline_img_adjust_x": 0,
                "word_highlights": [],
                "word_highlights2": [
                    [],
                    [0,1],
                    [0,1],
                    [],
                    [],
                    [],
                    [1,2]
                ]
            },
            "variables": []
        },
        "tutorial1jz": {
            "sign": [
                "Понаблюдайте за темпом",
                "атак врага через",
                "дверь справа от вас.",
                "",
                "Пройдите через",
                "дверь слева от вас,",
                "когда будете готовы."
            ],
            "attributes": {
                "font": "fonts/pixelmix.ttf#16#2",
                "font_highlight2_color": {
                    "r": 64,
                    "g": 192,
                    "b": 255,
                    "a": 255
                },
                "horizontal_justify": "center",
                "vertical_justify": "center",
                "line_padding": 0,
                "top_padding": 0,
                "inline_img_adjust_x": 0,
                "word_highlights": [],
                "word_highlights2": [
                    [0],
                    [0,1],
                    [4],
                    [],
                    [],
                    [],
                    [0,1]
                ]
            },
            "variables": []
        },
        "tutorial1kz": {
            "sign": [
                "Снаряжение может изнашиваться",
                "и в конце концов сломаться.",
                "",
                "Оружие наносит меньше урона",
                "при более низком качестве."
            ],
            "attributes": {
                "font": "fonts/pixelmix.ttf#16#2",
                "font_highlight2_color": {
                    "r": 64,
                    "g": 192,
                    "b": 255,
                    "a": 255
                },
                "horizontal_justify": "center",
                "vertical_justify": "center",
                "line_padding": 0,
                "top_padding": 0,
                "inline_img_adjust_x": 0,
                "word_highlights": [],
                "word_highlights2": [
                    [2],
                    [2],
                    [],
                    [2,3],
                    [1,2]
                ]
            },
            "variables": []
        },
        "tutorial1ky": {
            "sign": [
                "Навыки владения оружием увеличивают",
                "урон оружия.",
                "Оружие также изнашивается",
                "реже с более высоким",
                "навыком.",
                "",
                "Узнайте больше о навыках",
                "из списка навыков.",
                "",
                "$$$$$$$$"
            ],
            "attributes": {
                "font": "fonts/pixelmix.ttf#16#2",
                "font_highlight2_color": {
                    "r": 64,
                    "g": 192,
                    "b": 255,
                    "a": 255
                },
                "horizontal_justify": "center",
                "vertical_justify": "center",
                "line_padding": 0,
                "top_padding": 0,
                "inline_img_adjust_x": 0,
                "word_highlights": [
                    [],
                    [],
                    [],
                    [],
                    [],
                    [],
                    [],
                    [2,3]
                ],
                "word_highlights2": [
                    [1,2],
                    [1],
                    [2],
                    [0,1]
                ],
                "video": {
                    "background_img": "data/scripts/video_frame_noalpha.png",
                    "background_border": 8,
                    "path": "data/scripts/tutorial1/skillslist_mk.ogv",
                    "x": 0,
                    "y": 0,
                    "w": 0,
                    "h": 0
                }
            },
            "variables": [
                {
                    "type": "image",
                    "value": "*#images/ui/SkillSheet/Icons/Swords02_32.png",
                    "sizex": 0,
                    "sizey": 0
                },
                {
                    "type": "image",
                    "value": "*#images/ui/SkillSheet/Icons/Maces02_32.png",
                    "sizex": 0,
                    "sizey": 0
                },
                {
                    "type": "image",
                    "value": "*#images/ui/SkillSheet/Icons/Polearms02_32.png",
                    "sizex": 0,
                    "sizey": 0
                },
                {
                    "type": "image",
                    "value": "*#images/ui/SkillSheet/Icons/Axes02_32.png",
                    "sizex": 0,
                    "sizey": 0
                },
                {
                    "type": "image",
                    "value": "*#images/ui/SkillSheet/Icons/Ranged02_32.png",
                    "sizex": 0,
                    "sizey": 0
                },
                {
                    "type": "image",
                    "value": "*#images/ui/SkillSheet/Icons/Unarmed02_32.png",
                    "sizex": 0,
                    "sizey": 0
                },
                {
                    "type": "image",
                    "value": "*#images/ui/SkillSheet/Icons/Blocking02_32.png",
                    "sizex": 0,
                    "sizey": 0
                }
            ]
        },
        "tutorial1ky_gamepad": {
            "sign": [
                "Навыки владения оружием увеличивают",
                "урон оружия.",
                "Оружие также изнашивается",
                "реже с более высоким",
                "навыком.",
                "",
                "Узнайте больше о навыках",
                "из списка навыков.",
                "",
                "$$$$$$$$"
            ],
            "attributes": {
                "font": "fonts/pixelmix.ttf#16#2",
                "font_highlight2_color": {
                    "r": 64,
                    "g": 192,
                    "b": 255,
                    "a": 255
                },
                "horizontal_justify": "center",
                "vertical_justify": "center",
                "line_padding": 0,
                "top_padding": 0,
                "inline_img_adjust_x": 0,
                "word_highlights": [
                    [],
                    [],
                    [],
                    [],
                    [],
                    [],
                    [],
                    [2,3]
                ],
                "word_highlights2": [
                    [1,2],
                    [1],
                    [2],
                    [0,1]
                ],
                "video": {
                    "background_img": "data/scripts/video_frame_noalpha.png",
                    "background_border": 8,
                    "path": "data/scripts/tutorial1/skillslist_gamepad.ogv",
                    "x": 0,
                    "y": 0,
                    "w": 0,
                    "h": 0
                }
            },
            "variables": [
                {
                    "type": "image",
                    "value": "*#images/ui/SkillSheet/Icons/Swords02_32.png",
                    "sizex": 0,
                    "sizey": 0
                },
                {
                    "type": "image",
                    "value": "*#images/ui/SkillSheet/Icons/Maces02_32.png",
                    "sizex": 0,
                    "sizey": 0
                },
                {
                    "type": "image",
                    "value": "*#images/ui/SkillSheet/Icons/Polearms02_32.png",
                    "sizex": 0,
                    "sizey": 0
                },
                {
                    "type": "image",
                    "value": "*#images/ui/SkillSheet/Icons/Axes02_32.png",
                    "sizex": 0,
                    "sizey": 0
                },
                {
                    "type": "image",
                    "value": "*#images/ui/SkillSheet/Icons/Ranged02_32.png",
                    "sizex": 0,
                    "sizey": 0
                },
                {
                    "type": "image",
                    "value": "*#images/ui/SkillSheet/Icons/Unarmed02_32.png",
                    "sizex": 0,
                    "sizey": 0
                },
                {
                    "type": "image",
                    "value": "*#images/ui/SkillSheet/Icons/Blocking02_32.png",
                    "sizex": 0,
                    "sizey": 0
                }
            ]
        },
        "tutorial1k": {
            "sign": [
                "Блокирование может свести",
                "урон от атаки к нулю.",
                "",
                "Удерживайте$, чтобы Блокировать",
                "столько, сколько нужно,",
                "чтобы отсрочить смерть."
            ],
            "attributes": {
                "font": "fonts/pixelmix.ttf#16#2",
                "font_highlight2_color": {
                    "r": 64,
                    "g": 192,
                    "b": 255,
                    "a": 255
                },
                "horizontal_justify": "center",
                "vertical_justify": "center",
                "line_padding": 0,
                "top_padding": 0,
                "inline_img_adjust_x": 0,
                "word_highlights": [
                    [],
                    [],
                    [],
                    [0,2]
                ],
                "word_highlights2": [
                    [0],
                    [1,3],
                    [],
                    [],
                    [],
                    [1,2]
                ],
                "video": {
                    "background_img": "data/scripts/video_frame_half_noalpha.png",
                    "background_border": 8,
                    "path": "data/scripts/tutorial1/block.ogv",
                    "x": 0,
                    "y": 0,
                    "w": 0,
                    "h": 0
                }
            },
            "variables": [
                {
                    "type": "input_glyph",
                    "value": "Defend"
                }
            ]
        },
        "tutorial1l": {
            "sign": [
                "Враги устойчивы",
                "или уязвимы к",
                "разным типам оружия.",
                "$",
                "Это может быть решающим",
                "в победе или поражении."
            ],
            "attributes": {
                "font": "fonts/pixelmix.ttf#16#2",
                "font_highlight2_color": {
                    "r": 64,
                    "g": 192,
                    "b": 255,
                    "a": 255
                },
                "horizontal_justify": "center",
                "vertical_justify": "center",
                "line_padding": 0,
                "top_padding": 0,
                "inline_img_adjust_x": 0,
                "word_highlights": [],
                "word_highlights2": [
                    [2],
                    [0,1],
                    [1,2],
                    [],
                    [3],
                    [1]
                ]
            },
            "variables": [
                {
                    "type": "image",
                    "value": "*#data/scripts/tutorial1/sign_mace.png",
                    "sizex": 189,
                    "sizey": 87
                }
            ]
        },
        "tutorial1m": {
            "sign": [
                "Правильное использование атак,",
                "типов оружия, критических",
                "ударов и блокирования поможет",
                "вам выжить",
                "в подземелье."
            ],
            "attributes": {
                "font": "fonts/pixelmix.ttf#16#2",
                "font_highlight2_color": {
                    "r": 64,
                    "g": 192,
                    "b": 255,
                    "a": 255
                },
                "horizontal_justify": "center",
                "vertical_justify": "center",
                "line_padding": 0,
                "top_padding": 0,
                "inline_img_adjust_x": 0,
                "word_highlights": [],
                "word_highlights2": [
                    [2],
                    [0,1,2],
                    [0,2],
                    [2]
                ]
            },
            "variables": []
        },
        "tutorial1mo": {
            "sign": [
                "Поздравляем!",
                "Вы только что прошли",
                "Вводное Испытание.",
                "",
                "Испытание 1:",
                "Основы Подземелий",
                "и Ближний Бой"
            ],
            "attributes": {
                "font": "fonts/pixelmix.ttf#16#2",
                "font_highlight2_color": {
                    "r": 64,
                    "g": 192,
                    "b": 255,
                    "a": 255
                },
                "horizontal_justify": "center",
                "vertical_justify": "center",
                "line_padding": 0,
                "top_padding": 0,
                "inline_img_adjust_x": 0,
                "word_highlights": [],
                "word_highlights2": [
                    [2],
                    [0,1,2],
                    [0,1,2],
                    [0,2],
                    [2]
                ]
            },
            "variables": []
        },
        "tutorial1n": {
            "sign": [
                "Люки обычно ведут",
                "вас на следующий уровень.",
                "",
                "Этот ведет вас в",
                "Центр Зала Испытаний,",
                "где вы можете исследовать",
                "больше Испытаний."
            ],
            "attributes": {
                "font": "fonts/pixelmix.ttf#16#2",
                "font_highlight2_color": {
                    "r": 64,
                    "g": 192,
                    "b": 255,
                    "a": 255
                },
                "horizontal_justify": "center",
                "vertical_justify": "center",
                "line_padding": 0,
                "top_padding": 0,
                "inline_img_adjust_x": 0,
                "word_highlights": [],
                "word_highlights2": [
                    [0,1],
                    [],
                    [1,2],
                    [],
                    [0,1],
                    [1,2,3,4],
                    [],
                    [0,1]
                ]
            },
            "variables": []
        }
    }
}